densmap/__init__.py
densmap/densmap_.py
densmap/distances.py
densmap/load_trial.py
densmap/nndescent.py
densmap/rp_tree.py
densmap/sparse.py
densmap/spectral.py
densmap/trial_data.txt
densmap/utils.py
densmap/validation.py
densmap_learn-0.2.2.data/data/trial_data.txt
densmap_learn-0.2.2.dist-info/LICENSE
densmap_learn-0.2.2.dist-info/METADATA
densmap_learn-0.2.2.dist-info/WHEEL
densmap_learn-0.2.2.dist-info/top_level.txt
densmap_learn-0.2.2.dist-info/RECORD
