Metadata-Version: 2.1
Name: densmap-learn
Version: 0.2.2
Summary: densMAP
Home-page: http://github.com/hhcho/densvis
Maintainer: Ashwin Narayan
Maintainer-email: ashwinn@mit.edu
License: MIT
Keywords: dimension reduction t-sne manifold density
Platform: UNKNOWN
Classifier: Intended Audience :: Science/Research
Classifier: Intended Audience :: Developers
Classifier: License :: OSI Approved :: MIT License
Classifier: Programming Language :: C
Classifier: Programming Language :: Python
Classifier: Topic :: Software Development
Classifier: Topic :: Scientific/Engineering
Classifier: Operating System :: Microsoft :: Windows
Classifier: Operating System :: POSIX
Classifier: Operating System :: Unix
Classifier: Operating System :: MacOS
Classifier: Programming Language :: Python :: 2.7
Classifier: Programming Language :: Python :: 3.6
Requires-Dist: numpy (>=1.13)
Requires-Dist: scikit-learn (>=0.16)
Requires-Dist: scipy (>=0.19)
Requires-Dist: numba (==0.48.0)
